{
  "$schema": "https://json-schema.org/draft/2020-12/schema",
  "$id": "https://github.com/jbeshir/demesne/docs/reference/tools/sandbox_upload.schema.json",
  "title": "sandbox_upload input",
  "type": "object",
  "properties": {
    "sandbox_id": {
      "type": "string",
      "description": "Sandbox handle returned by sandbox_create."
    },
    "src": {
      "type": "string",
      "description": "Host file path to upload. Must be absolute and inside DEMESNE_ALLOWED_PATHS. Symlinks are resolved before the check. The live MCP input schema populates this description with the configured DEMESNE_ALLOWED_PATHS roots (or a no-host-inputs warning when none are configured); the tool-level description carries the same clause."
    },
    "dst": {
      "type": "string",
      "description": "Destination path inside the sandbox. Must be absolute. Parent directory must already exist."
    }
  },
  "required": ["sandbox_id", "src", "dst"],
  "additionalProperties": false
}
